assignment-2/data_memory.sv
// =============================================================
// Byte-addressable RAM with a bidirectional (tri-state) data
// bus, gated by chip-select (cs) and rd_wr_bar (1 = read, 0 = write).
// When not selected/read, data_bus is driven to high-Z ('z) so
// other devices on the same bus (e.g. the register bank) can drive it.
// =============================================================
module memory #(
    parameter int AD_LINES   = 16,
    parameter int DATA_LINES = 8
) (
    input logic rd_wr_bar,
    input logic [AD_LINES - 1 : 0] addr_bus,
    inout wire [DATA_LINES - 1 : 0] data_bus,
    input logic clk,
    input logic cs
);

  logic [DATA_LINES - 1:0] mem[0:(1<<AD_LINES) -1];

  // Drive the bus only when selected for a read; otherwise release it.
  assign data_bus = (cs && rd_wr_bar) ? mem[addr_bus] : 'z;

  // Synchronous write: on a clock edge, if selected and rd_wr_bar
  // indicates "write" (0), latch whatever is currently on the bus.
  always_ff @(posedge clk) begin
    if (cs && !rd_wr_bar) begin
      mem[addr_bus] <= data_bus;
    end
  end
endmodule

assignment-2/data_memory_tb.sv
// =============================================================
// Testbench for data_memory.sv: writes 4 known values to
// different addresses, reads them back, and asserts they match.
// =============================================================
`timescale 1ns / 1ps

module memory_tb;

  localparam AD_LINES = 16;
  localparam DATA_LINES = 8;

  logic rd_wr_bar;
  logic [AD_LINES-1:0] addr_bus;
  logic clk;
  logic cs;

  tri [DATA_LINES-1:0] data_bus;
  logic [DATA_LINES-1:0] data_drv;

  // Testbench only drives the bus during writes; the DUT drives
  // it during reads (see data_memory.sv's tri-state assign).
  assign data_bus = (!rd_wr_bar && cs) ? data_drv : 'z;

  memory #(
      .AD_LINES  (AD_LINES),
      .DATA_LINES(DATA_LINES)
  ) dut (
      .rd_wr_bar(rd_wr_bar),
      .addr_bus(addr_bus),
      .data_bus(data_bus),
      .clk(clk),
      .cs(cs)
  );

  // Clock generation: 10ns period
  initial begin
    clk = 0;
    forever #5 clk = ~clk;
  end

  // Write task: assert cs+write, drive address/data, wait for a
  // clock edge so the DUT latches it, then release.
  task automatic mem_write(input [AD_LINES-1:0] wr_addr, input [DATA_LINES-1:0] wr_data);
    begin
      @(negedge clk);
      cs        = 1;
      rd_wr_bar = 0;
      addr_bus  = wr_addr;
      data_drv  = wr_data;

      @(posedge clk);  // write occurs here

      @(negedge clk);
      cs       = 0;
      data_drv = 'z;
    end
  endtask

  // Read task: assert cs+read, drive address, let the DUT's
  // combinational read settle, then sample the bus.
  task automatic mem_read(input [AD_LINES-1:0] rd_addr, output [DATA_LINES-1:0] rd_data);
    begin
      @(negedge clk);
      cs        = 1;
      rd_wr_bar = 1;
      addr_bus  = rd_addr;

      #1;  // allow combinational read to propagate
      rd_data = data_bus;

      @(negedge clk);
      cs = 0;
    end
  endtask

  logic [7:0] rdata;

  initial begin
    $dumpfile("memory.vcd");
    $dumpvars(0, memory_tb);

    cs        = 0;
    rd_wr_bar = 1;
    addr_bus  = 0;
    data_drv  = 'z;

    // Write some values
    mem_write(16'h0000, 8'hAA);
    mem_write(16'h0001, 8'h55);
    mem_write(16'h1234, 8'hDE);
    mem_write(16'hFFFF, 8'hAD);

    // Read them back
    mem_read(16'h0000, rdata);
    $display("Addr=0000 Data=%h Expected=AA", rdata);

    mem_read(16'h0001, rdata);
    $display("Addr=0001 Data=%h Expected=55", rdata);

    mem_read(16'h1234, rdata);
    $display("Addr=1234 Data=%h Expected=DE", rdata);

    mem_read(16'hFFFF, rdata);
    $display("Addr=FFFF Data=%h Expected=AD", rdata);

    // Assertions
    mem_read(16'h0000, rdata);
    assert (rdata == 8'hAA);

    mem_read(16'h0001, rdata);
    assert (rdata == 8'h55);

    mem_read(16'h1234, rdata);
    assert (rdata == 8'hDE);

    mem_read(16'hFFFF, rdata);
    assert (rdata == 8'hAD);

    $display("TEST PASSED");
    $finish;
  end

endmodule

assignment-2/memory.vcd
$date
	Thu Jul  2 21:26:09 2026
$end
$version
	Icarus Verilog
$end
$timescale
	1ps
$end
$scope module memory_tb $end
$var wire 8 ! data_bus [7:0] $end
$var parameter 32 " AD_LINES $end
$var parameter 32 # DATA_LINES $end
$var reg 16 $ addr_bus [15:0] $end
$var reg 1 % clk $end
$var reg 1 & cs $end
$var reg 8 ' data_drv [7:0] $end
$var reg 1 ( rd_wr_bar $end
$var reg 8 ) rdata [7:0] $end
$scope module dut $end
$var wire 16 * addr_bus [15:0] $end
$var wire 1 % clk $end
$var wire 1 & cs $end
$var wire 8 + data_bus [7:0] $end
$var wire 1 ( rd_wr_bar $end
$var parameter 32 , AD_LINES $end
$var parameter 32 - DATA_LINES $end
$upscope $end
$scope task mem_read $end
$upscope $end
$scope task mem_write $end
$upscope $end
$upscope $end
$enddefinitions $end
$comment Show the parameter values. $end
$dumpall
b1000 -
b10000 ,
b1000 #
b10000 "
$end
#0
$dumpvars
bz +
b0 *
bx )
1(
bz '
0&
0%
b0 $
bz !
$end
#5000
1%
#10000
b10101010 !
b10101010 +
b10101010 '
0(
1&
0%
#15000
1%
#20000
bz !
bz +
bz '
0&
0%
#25000
1%
#30000
b1010101 !
b1010101 +
b1010101 '
b1 $
b1 *
1&
0%
#35000
1%
#40000
bz !
bz +
bz '
0&
0%
#45000
1%
#50000
b11011110 !
b11011110 +
b11011110 '
b1001000110100 $
b1001000110100 *
1&
0%
#55000
1%
#60000
bz !
bz +
bz '
0&
0%
#65000
1%
#70000
b10101101 !
b10101101 +
b10101101 '
b1111111111111111 $
b1111111111111111 *
1&
0%
#75000
1%
#80000
bz !
bz +
bz '
0&
0%
#85000
1%
#90000
b10101010 !
b10101010 +
b0 $
b0 *
1(
1&
0%
#95000
1%
#100000
bz !
bz +
b10101010 )
0&
0%
#105000
1%
#110000
b1010101 !
b1010101 +
b1 $
b1 *
1&
0%
#115000
1%
#120000
bz !
bz +
b1010101 )
0&
0%
#125000
1%
#130000
b11011110 !
b11011110 +
b1001000110100 $
b1001000110100 *
1&
0%
#135000
1%
#140000
bz !
bz +
b11011110 )
0&
0%
#145000
1%
#150000
b10101101 !
b10101101 +
b1111111111111111 $
b1111111111111111 *
1&
0%
#155000
1%
#160000
bz !
bz +
b10101101 )
0&
0%
#165000
1%
#170000
b10101010 !
b10101010 +
b0 $
b0 *
1&
0%
#175000
1%
#180000
bz !
bz +
b10101010 )
0&
0%
#185000
1%
#190000
b1010101 !
b1010101 +
b1 $
b1 *
1&
0%
#195000
1%
#200000
bz !
bz +
b1010101 )
0&
0%
#205000
1%
#210000
b11011110 !
b11011110 +
b1001000110100 $
b1001000110100 *
1&
0%
#215000
1%
#220000
bz !
bz +
b11011110 )
0&
0%
#225000
1%
#230000
b10101101 !
b10101101 +
b1111111111111111 $
b1111111111111111 *
1&
0%
#235000
1%
#240000
bz !
bz +
b10101101 )
0&
0%
