assignment-4/fft8_dit.v
// 8-point radix-2 Decimation-in-Time FFT
// Fixed-point complex arithmetic using signed Q15 twiddle constants.

module fft8_dit #(
    parameter integer DATA_WIDTH = 16
)(
    input  wire                           clk,
    input  wire                           rst,
    input  wire                           load,

    // Packed complex input samples:
    // sample n occupies bits n*DATA_WIDTH +: DATA_WIDTH.
    input  wire signed [8*DATA_WIDTH-1:0] x_re,
    input  wire signed [8*DATA_WIDTH-1:0] x_im,

    output reg                            done,

    output reg signed [DATA_WIDTH-1:0] X0_re, X0_im,
    output reg signed [DATA_WIDTH-1:0] X1_re, X1_im,
    output reg signed [DATA_WIDTH-1:0] X2_re, X2_im,
    output reg signed [DATA_WIDTH-1:0] X3_re, X3_im,
    output reg signed [DATA_WIDTH-1:0] X4_re, X4_im,
    output reg signed [DATA_WIDTH-1:0] X5_re, X5_im,
    output reg signed [DATA_WIDTH-1:0] X6_re, X6_im,
    output reg signed [DATA_WIDTH-1:0] X7_re, X7_im
);

    localparam [2:0] S_IDLE   = 3'd0;
    localparam [2:0] S_LOAD   = 3'd1;
    localparam [2:0] S_STAGE1 = 3'd2;
    localparam [2:0] S_STAGE2 = 3'd3;
    localparam [2:0] S_STAGE3 = 3'd4;
    localparam [2:0] S_DONE   = 3'd5;

    // cos(pi/4) and sin(pi/4) represented in Q15.
    localparam signed [15:0] TWIDDLE_45 = 16'sd23170;

    reg [2:0] state;
    reg [3:0] sample_index;

    reg signed [DATA_WIDTH-1:0] input_re [0:7];
    reg signed [DATA_WIDTH-1:0] input_im [0:7];

    reg signed [DATA_WIDTH-1:0] stage1_re [0:7];
    reg signed [DATA_WIDTH-1:0] stage1_im [0:7];

    reg signed [DATA_WIDTH-1:0] stage2_re [0:7];
    reg signed [DATA_WIDTH-1:0] stage2_im [0:7];

    reg signed [DATA_WIDTH-1:0] stage3_re [0:7];
    reg signed [DATA_WIDTH-1:0] stage3_im [0:7];

    // Wider temporaries avoid losing the product before the Q15 shift.
    reg signed [31:0] mult_re;
    reg signed [31:0] mult_im;

    integer i;

    function [2:0] reverse3(input [2:0] value);
        begin
            reverse3 = {value[0], value[1], value[2]};
        end
    endfunction

    always @(posedge clk or posedge rst) begin
        if (rst) begin
            state        <= S_IDLE;
            sample_index <= 0;
            done         <= 1'b0;

            X0_re <= 0; X0_im <= 0;
            X1_re <= 0; X1_im <= 0;
            X2_re <= 0; X2_im <= 0;
            X3_re <= 0; X3_im <= 0;
            X4_re <= 0; X4_im <= 0;
            X5_re <= 0; X5_im <= 0;
            X6_re <= 0; X6_im <= 0;
            X7_re <= 0; X7_im <= 0;
        end
        else begin
            case (state)

                S_IDLE: begin
                    done         <= 1'b0;
                    sample_index <= 0;

                    if (load)
                        state <= S_LOAD;
                end

                // Load one sample per clock and place it in bit-reversed order.
                S_LOAD: begin
                    input_re[reverse3(sample_index[2:0])] <=
                        x_re[sample_index[2:0]*DATA_WIDTH +: DATA_WIDTH];

                    input_im[reverse3(sample_index[2:0])] <=
                        x_im[sample_index[2:0]*DATA_WIDTH +: DATA_WIDTH];

                    if (sample_index == 7) begin
                        sample_index <= 0;
                        state <= S_STAGE1;
                    end
                    else begin
                        sample_index <= sample_index + 1'b1;
                    end
                end

                // Butterfly distance = 1.
                S_STAGE1: begin
                    for (i = 0; i < 8; i = i + 2) begin
                        stage1_re[i]   <= input_re[i] + input_re[i+1];
                        stage1_im[i]   <= input_im[i] + input_im[i+1];
                        stage1_re[i+1] <= input_re[i] - input_re[i+1];
                        stage1_im[i+1] <= input_im[i] - input_im[i+1];
                    end

                    state <= S_STAGE2;
                end

                // Butterfly distance = 2.
                // Multiplication by -j is implemented as (b, -a).
                S_STAGE2: begin
                    for (i = 0; i < 8; i = i + 4) begin
                        stage2_re[i]   <= stage1_re[i] + stage1_re[i+2];
                        stage2_im[i]   <= stage1_im[i] + stage1_im[i+2];

                        stage2_re[i+2] <= stage1_re[i] - stage1_re[i+2];
                        stage2_im[i+2] <= stage1_im[i] - stage1_im[i+2];

                        stage2_re[i+1] <= stage1_re[i+1] + stage1_im[i+3];
                        stage2_im[i+1] <= stage1_im[i+1] - stage1_re[i+3];

                        stage2_re[i+3] <= stage1_re[i+1] - stage1_im[i+3];
                        stage2_im[i+3] <= stage1_im[i+1] + stage1_re[i+3];
                    end

                    state <= S_STAGE3;
                end

                // Final radix-2 stage.
                // W8^0 = 1, W8^1 = (1-j)/sqrt(2),
                // W8^2 = -j, W8^3 = (-1-j)/sqrt(2).
                S_STAGE3: begin
                    stage3_re[0] <= stage2_re[0] + stage2_re[4];
                    stage3_im[0] <= stage2_im[0] + stage2_im[4];
                    stage3_re[4] <= stage2_re[0] - stage2_re[4];
                    stage3_im[4] <= stage2_im[0] - stage2_im[4];

                    // W8^1 = (1-j)/sqrt(2)
                    mult_re = $signed(stage2_re[5] + stage2_im[5])
                              * $signed(TWIDDLE_45);
                    mult_im = $signed(stage2_im[5] - stage2_re[5])
                              * $signed(TWIDDLE_45);

                    stage3_re[1] <= stage2_re[1] + (mult_re >>> 15);
                    stage3_im[1] <= stage2_im[1] + (mult_im >>> 15);
                    stage3_re[5] <= stage2_re[1] - (mult_re >>> 15);
                    stage3_im[5] <= stage2_im[1] - (mult_im >>> 15);

                    // W8^2 = -j
                    stage3_re[2] <= stage2_re[2] + stage2_im[6];
                    stage3_im[2] <= stage2_im[2] - stage2_re[6];
                    stage3_re[6] <= stage2_re[2] - stage2_im[6];
                    stage3_im[6] <= stage2_im[2] + stage2_re[6];

                    // W8^3 = (-1-j)/sqrt(2)
                    mult_re = $signed(stage2_im[7] - stage2_re[7])
                              * $signed(TWIDDLE_45);
                    mult_im = $signed(-stage2_re[7] - stage2_im[7])
                              * $signed(TWIDDLE_45);

                    stage3_re[3] <= stage2_re[3] + (mult_re >>> 15);
                    stage3_im[3] <= stage2_im[3] + (mult_im >>> 15);
                    stage3_re[7] <= stage2_re[3] - (mult_re >>> 15);
                    stage3_im[7] <= stage2_im[3] - (mult_im >>> 15);

                    state <= S_DONE;
                end

                S_DONE: begin
                    done <= 1'b1;

                    X0_re <= stage3_re[0]; X0_im <= stage3_im[0];
                    X1_re <= stage3_re[1]; X1_im <= stage3_im[1];
                    X2_re <= stage3_re[2]; X2_im <= stage3_im[2];
                    X3_re <= stage3_re[3]; X3_im <= stage3_im[3];
                    X4_re <= stage3_re[4]; X4_im <= stage3_im[4];
                    X5_re <= stage3_re[5]; X5_im <= stage3_im[5];
                    X6_re <= stage3_re[6]; X6_im <= stage3_im[6];
                    X7_re <= stage3_re[7]; X7_im <= stage3_im[7];

                    // Return to idle after the result has been observed.
                    if (!load)
                        state <= S_IDLE;
                end

                default: begin
                    state <= S_IDLE;
                end

            endcase
        end
    end

endmodule

assignment-4/tb_fft8_dit.v
`timescale 1ns/1ps

module tb_fft8_dit;

    localparam integer DATA_WIDTH = 16;

    reg clk;
    reg rst;
    reg load;

    reg signed [8*DATA_WIDTH-1:0] x_re;
    reg signed [8*DATA_WIDTH-1:0] x_im;

    wire done;

    wire signed [DATA_WIDTH-1:0] X0_re, X0_im;
    wire signed [DATA_WIDTH-1:0] X1_re, X1_im;
    wire signed [DATA_WIDTH-1:0] X2_re, X2_im;
    wire signed [DATA_WIDTH-1:0] X3_re, X3_im;
    wire signed [DATA_WIDTH-1:0] X4_re, X4_im;
    wire signed [DATA_WIDTH-1:0] X5_re, X5_im;
    wire signed [DATA_WIDTH-1:0] X6_re, X6_im;
    wire signed [DATA_WIDTH-1:0] X7_re, X7_im;

    fft8_dit #(.DATA_WIDTH(DATA_WIDTH)) dut (
        .clk(clk),
        .rst(rst),
        .load(load),
        .x_re(x_re),
        .x_im(x_im),
        .done(done),

        .X0_re(X0_re), .X0_im(X0_im),
        .X1_re(X1_re), .X1_im(X1_im),
        .X2_re(X2_re), .X2_im(X2_im),
        .X3_re(X3_re), .X3_im(X3_im),
        .X4_re(X4_re), .X4_im(X4_im),
        .X5_re(X5_re), .X5_im(X5_im),
        .X6_re(X6_re), .X6_im(X6_im),
        .X7_re(X7_re), .X7_im(X7_im)
    );

    // 10 ns clock period.
    always #5 clk = ~clk;

    initial begin
        $dumpfile("fft8_sim.vcd");
        $dumpvars(0, tb_fft8_dit);

        clk  = 1'b0;
        rst  = 1'b1;
        load = 1'b0;
        x_re = '0;
        x_im = '0;

        // Reset the design.
        #20;
        rst = 1'b0;

        // x[n] = 100(n+1) + j*100(8-n)
        x_re[0*DATA_WIDTH +: DATA_WIDTH] = 16'sd100;
        x_im[0*DATA_WIDTH +: DATA_WIDTH] = 16'sd800;

        x_re[1*DATA_WIDTH +: DATA_WIDTH] = 16'sd200;
        x_im[1*DATA_WIDTH +: DATA_WIDTH] = 16'sd700;

        x_re[2*DATA_WIDTH +: DATA_WIDTH] = 16'sd300;
        x_im[2*DATA_WIDTH +: DATA_WIDTH] = 16'sd600;

        x_re[3*DATA_WIDTH +: DATA_WIDTH] = 16'sd400;
        x_im[3*DATA_WIDTH +: DATA_WIDTH] = 16'sd500;

        x_re[4*DATA_WIDTH +: DATA_WIDTH] = 16'sd500;
        x_im[4*DATA_WIDTH +: DATA_WIDTH] = 16'sd400;

        x_re[5*DATA_WIDTH +: DATA_WIDTH] = 16'sd600;
        x_im[5*DATA_WIDTH +: DATA_WIDTH] = 16'sd300;

        x_re[6*DATA_WIDTH +: DATA_WIDTH] = 16'sd700;
        x_im[6*DATA_WIDTH +: DATA_WIDTH] = 16'sd200;

        x_re[7*DATA_WIDTH +: DATA_WIDTH] = 16'sd800;
        x_im[7*DATA_WIDTH +: DATA_WIDTH] = 16'sd100;

        // Keep load asserted for one clock so all eight samples are captured.
        #10;
        load = 1'b1;
        #10;
        load = 1'b0;

        // The FFT takes the load cycle plus three processing stages.
        @(posedge done);
        #1;

        $display("");
        $display("==============================================");
        $display("          8-POINT DIT FFT RESULTS");
        $display("==============================================");
        $display("Input: x[n] = 100(n+1) + j*100(8-n)");
        $display("----------------------------------------------");
        $display("X[0] = %6d + j(%6d)", X0_re, X0_im);
        $display("X[1] = %6d + j(%6d)", X1_re, X1_im);
        $display("X[2] = %6d + j(%6d)", X2_re, X2_im);
        $display("X[3] = %6d + j(%6d)", X3_re, X3_im);
        $display("X[4] = %6d + j(%6d)", X4_re, X4_im);
        $display("X[5] = %6d + j(%6d)", X5_re, X5_im);
        $display("X[6] = %6d + j(%6d)", X6_re, X6_im);
        $display("X[7] = %6d + j(%6d)", X7_re, X7_im);
        $display("----------------------------------------------");
        $display("FFT completed successfully.");
        $display("==============================================");
        $display("");

        #20;
        $finish;
    end

endmodule

assignment-4/fft8_sim.vcd
$date
	Sun Aug  9 20:17:47 2026
$end
$version
	Icarus Verilog
$end
$timescale
	1ps
$end
$scope module tb_fft8_dit $end
$var wire 1 ! done $end
$var wire 16 " X7_re [15:0] $end
$var wire 16 # X7_im [15:0] $end
$var wire 16 $ X6_re [15:0] $end
$var wire 16 % X6_im [15:0] $end
$var wire 16 & X5_re [15:0] $end
$var wire 16 ' X5_im [15:0] $end
$var wire 16 ( X4_re [15:0] $end
$var wire 16 ) X4_im [15:0] $end
$var wire 16 * X3_re [15:0] $end
$var wire 16 + X3_im [15:0] $end
$var wire 16 , X2_re [15:0] $end
$var wire 16 - X2_im [15:0] $end
$var wire 16 . X1_re [15:0] $end
$var wire 16 / X1_im [15:0] $end
$var wire 16 0 X0_re [15:0] $end
$var wire 16 1 X0_im [15:0] $end
$var parameter 32 2 DATA_WIDTH $end
$var reg 1 3 clk $end
$var reg 1 4 load $end
$var reg 1 5 rst $end
$var reg 128 6 x_im [127:0] $end
$var reg 128 7 x_re [127:0] $end
$scope module dut $end
$var wire 1 3 clk $end
$var wire 1 4 load $end
$var wire 1 5 rst $end
$var wire 128 8 x_im [127:0] $end
$var wire 128 9 x_re [127:0] $end
$var parameter 32 : DATA_WIDTH $end
$var parameter 3 ; S_DONE $end
$var parameter 3 < S_IDLE $end
$var parameter 3 = S_LOAD $end
$var parameter 3 > S_STAGE1 $end
$var parameter 3 ? S_STAGE2 $end
$var parameter 3 @ S_STAGE3 $end
$var parameter 16 A TWIDDLE_45 $end
$var reg 16 B X0_im [15:0] $end
$var reg 16 C X0_re [15:0] $end
$var reg 16 D X1_im [15:0] $end
$var reg 16 E X1_re [15:0] $end
$var reg 16 F X2_im [15:0] $end
$var reg 16 G X2_re [15:0] $end
$var reg 16 H X3_im [15:0] $end
$var reg 16 I X3_re [15:0] $end
$var reg 16 J X4_im [15:0] $end
$var reg 16 K X4_re [15:0] $end
$var reg 16 L X5_im [15:0] $end
$var reg 16 M X5_re [15:0] $end
$var reg 16 N X6_im [15:0] $end
$var reg 16 O X6_re [15:0] $end
$var reg 16 P X7_im [15:0] $end
$var reg 16 Q X7_re [15:0] $end
$var reg 1 ! done $end
$var reg 32 R mult_im [31:0] $end
$var reg 32 S mult_re [31:0] $end
$var reg 4 T sample_index [3:0] $end
$var reg 3 U state [2:0] $end
$var integer 32 V i [31:0] $end
$scope function reverse3 $end
$var reg 3 W value [2:0] $end
$upscope $end
$upscope $end
$upscope $end
$enddefinitions $end
$comment Show the parameter values. $end
$dumpall
b101101010000010 A
b100 @
b11 ?
b10 >
b1 =
b0 <
b101 ;
b10000 :
b10000 2
$end
#0
$dumpvars
bx W
bx V
b0 U
b0 T
bx S
bx R
b0 Q
b0 P
b0 O
b0 N
b0 M
b0 L
b0 K
b0 J
b0 I
b0 H
b0 G
b0 F
b0 E
b0 D
b0 C
b0 B
b0 9
b0 8
b0 7
b0 6
15
04
03
b0 1
b0 0
b0 /
b0 .
b0 -
b0 ,
b0 +
b0 *
b0 )
b0 (
b0 '
b0 &
b0 %
b0 $
b0 #
b0 "
0!
$end
#5000
13
#10000
03
#15000
13
#20000
03
b11001000000000011001000000000010010110000000001100100000000000111110100000000100101100000000010101111000000001100100000 6
b11001000000000011001000000000010010110000000001100100000000000111110100000000100101100000000010101111000000001100100000 8
b11001000000000001010111100000000100101100000000001111101000000000110010000000000010010110000000000110010000000000001100100 7
b11001000000000001010111100000000100101100000000001111101000000000110010000000000010010110000000000110010000000000001100100 9
05
#25000
13
#30000
03
14
#35000
b1 U
13
#40000
03
04
#45000
b1 T
b0 W
13
#50000
03
#55000
b10 T
b1 W
13
#60000
03
#65000
b11 T
b10 W
13
#70000
03
#75000
b100 T
b11 W
13
#80000
03
#85000
b101 T
b100 W
13
#90000
03
#95000
b110 T
b101 W
13
#100000
03
#105000
b111 T
b110 W
13
#110000
03
#115000
b10 U
b0 T
b111 W
13
#120000
03
#125000
b11 U
b1000 V
13
#130000
03
#135000
b100 U
b1000 V
13
#140000
03
#145000
b101 U
b1000110101101011001000000 R
b1000110101101011001000000 S
13
#150000
03
#155000
b0 U
b1111110111001011 #
b1111110111001011 P
b1111101010101011 "
b1111101010101011 Q
b1111110011100000 $
b1111110011100000 O
b11101011 '
b11101011 L
b1111110111001011 &
b1111110111001011 M
b110010000 )
b110010000 J
b1111111001110000 (
b1111111001110000 K
b1000110101 +
b1000110101 H
b1111111100010101 *
b1111111100010101 I
b1100100000 -
b1100100000 F
b10101010101 /
b10101010101 D
b1000110101 .
b1000110101 E
b111000010000 1
b111000010000 B
b111000010000 0
b111000010000 C
1!
13
#160000
03
#165000
0!
13
