assignment-5/mux2.v
// mux2.v — generic WIDTH-bit 2-to-1 mux
module mux2 #(parameter WIDTH = 32) (
    input  wire             sel,
    input  wire [WIDTH-1:0] d0,
    input  wire [WIDTH-1:0] d1,
    output wire [WIDTH-1:0] y
);
    assign y = sel ? d1 : d0;
endmodule

assignment-5/adder.v
// adder.v — generic 32-bit adder (used for PC+4 and PC+imm)
module adder (
    input  wire [31:0] a,
    input  wire [31:0] b,
    output wire [31:0] sum
);
    assign sum = a + b;
endmodule

assignment-5/data_mem.v
// data_mem.v — Data Memory (byte-addressed, word read/write here)
module data_mem (
    input  wire        clk,
    input  wire        mem_write,
    input  wire [31:0] addr,
    input  wire [31:0] write_data,
    output wire [31:0] read_data
);
    reg [31:0] mem [0:255]; // 1KB data memory
    integer i;

    initial begin
        for (i = 0; i < 256; i = i + 1)
            mem[i] = 32'b0;
    end

    always @(posedge clk) begin
        if (mem_write)
            mem[addr[9:2]] <= write_data;
    end

    assign read_data = mem[addr[9:2]];
endmodule

assignment-5/alu.v
// alu.v — Arithmetic Logic Unit
module alu (
    input  wire [31:0] a,
    input  wire [31:0] b,
    input  wire [3:0]  alu_control,
    output reg  [31:0] result,
    output wire         zero
);
    // ALU control encoding:
    // 0000 = ADD   0001 = SUB   0010 = AND   0011 = OR
    // 0100 = XOR   0101 = SLL   0110 = SRL   0111 = SRA
    // 1000 = SLT   1001 = SLTU

    always @(*) begin
        case (alu_control)
            4'b0000: result = a + b;
            4'b0001: result = a - b;
            4'b0010: result = a & b;
            4'b0011: result = a | b;
            4'b0100: result = a ^ b;
            4'b0101: result = a << b[4:0];
            4'b0110: result = a >> b[4:0];
            4'b0111: result = $signed(a) >>> b[4:0];
            4'b1000: result = ($signed(a) < $signed(b)) ? 32'b1 : 32'b0;
            4'b1001: result = (a < b) ? 32'b1 : 32'b0;
            default: result = 32'b0;
        endcase
    end

    assign zero = (result == 32'b0);
endmodule

assignment-5/imm_gen.v
// imm_gen.v — Immediate Generator / Sign-Extend unit
module imm_gen (
    input  wire [31:0] instr,
    input  wire [1:0]  imm_src,   // 00 = I-type, 01 = S-type, 10 = B-type
    output reg  [31:0] imm_ext
);
    always @(*) begin
        case (imm_src)
            2'b00: // I-type (addi, lw, jalr): imm[11:0] = instr[31:20]
                imm_ext = {{20{instr[31]}}, instr[31:20]};

            2'b01: // S-type (sw): imm[11:5]=instr[31:25], imm[4:0]=instr[11:7]
                imm_ext = {{20{instr[31]}}, instr[31:25], instr[11:7]};

            2'b10: // B-type (beq/bne/...): imm[12|11|10:5|4:1|0], LSB=0
                imm_ext = {{19{instr[31]}}, instr[31], instr[7],
                           instr[30:25], instr[11:8], 1'b0};

            default:
                imm_ext = 32'b0;
        endcase
    end
endmodule

assignment-5/reg_file.v
// reg_file.v — 32 x 32-bit Register File, x0 hardwired to 0
module reg_file (
    input  wire        clk,
    input  wire        we3,        // RegWrite
    input  wire [4:0]  a1,         // rs1
    input  wire [4:0]  a2,         // rs2
    input  wire [4:0]  a3,         // rd  (write address)
    input  wire [31:0] wd3,        // write data
    output wire [31:0] rd1,        // read data 1
    output wire [31:0] rd2         // read data 2
);
    reg [31:0] regs [0:31];
    integer i;

    initial begin
        for (i = 0; i < 32; i = i + 1)
            regs[i] = 32'b0;
    end

    // Synchronous write, x0 never written
    always @(posedge clk) begin
        if (we3 && a3 != 5'b0)
            regs[a3] <= wd3;
    end

    // Combinational read, x0 always reads 0
    assign rd1 = (a1 == 5'b0) ? 32'b0 : regs[a1];
    assign rd2 = (a2 == 5'b0) ? 32'b0 : regs[a2];
endmodule

assignment-5/alu_control.v
// alu_control.v — decides the ALU operation from ALUOp + funct fields
module alu_control (
    input  wire [1:0] alu_op,     // from main Control Unit
    input  wire [2:0] funct3,     // instr[14:12]
    input  wire        funct7_5,   // instr[30]
    output reg  [3:0] alu_control
);
    always @(*) begin
        case (alu_op)
            2'b00: alu_control = 4'b0000;              // lw/sw -> add
            2'b01: alu_control = 4'b0001;              // branch -> subtract
            2'b10: begin                                 // R-type / I-type ALU
                case (funct3)
                    3'b000: alu_control = (funct7_5) ? 4'b0001 : 4'b0000; // sub/add
                    3'b111: alu_control = 4'b0010;      // and
                    3'b110: alu_control = 4'b0011;      // or
                    3'b100: alu_control = 4'b0100;      // xor
                    3'b001: alu_control = 4'b0101;      // sll
                    3'b101: alu_control = (funct7_5) ? 4'b0111 : 4'b0110; // sra/srl
                    3'b010: alu_control = 4'b1000;      // slt
                    3'b011: alu_control = 4'b1001;      // sltu
                    default: alu_control = 4'b0000;
                endcase
            end
            default: alu_control = 4'b0000;
        endcase
    end
endmodule

assignment-5/control_unit.v
// control_unit.v — Main Control Unit (decodes opcode only)
module control_unit (
    input  wire [6:0] opcode,
    output reg         reg_write,
    output reg         alu_src,
    output reg         mem_write,
    output reg         result_src,   // 0 = ALU result, 1 = memory data
    output reg         branch,
    output reg  [1:0]  imm_src,
    output reg  [1:0]  alu_op
);
    localparam R_TYPE   = 7'b0110011;
    localparam I_TYPE_A = 7'b0010011; // addi, andi, ori...
    localparam LOAD     = 7'b0000011; // lw
    localparam STORE    = 7'b0100011; // sw
    localparam BRANCH   = 7'b1100011; // beq, bne...

    always @(*) begin
        // safe defaults
        reg_write  = 1'b0;
        alu_src    = 1'b0;
        mem_write  = 1'b0;
        result_src = 1'b0;
        branch     = 1'b0;
        imm_src    = 2'b00;
        alu_op     = 2'b00;

        case (opcode)
            R_TYPE: begin
                reg_write = 1'b1;
                alu_src   = 1'b0;
                alu_op    = 2'b10;
            end
            I_TYPE_A: begin
                reg_write = 1'b1;
                alu_src   = 1'b1;
                imm_src   = 2'b00;
                alu_op    = 2'b10;
            end
            LOAD: begin
                reg_write  = 1'b1;
                alu_src    = 1'b1;
                imm_src    = 2'b00;
                result_src = 1'b1;
                alu_op     = 2'b00;
            end
            STORE: begin
                alu_src   = 1'b1;
                mem_write = 1'b1;
                imm_src   = 2'b01;
                alu_op    = 2'b00;
            end
            BRANCH: begin
                alu_src = 1'b0;
                branch  = 1'b1;
                imm_src = 2'b10;
                alu_op  = 2'b01;
            end
            default: ; // NOP / unsupported opcode -> all defaults (safe)
        endcase
    end
endmodule

assignment-5/instr_mem.v
// instr_mem.v — Instruction Memory (read-only, word-addressed via byte PC)
module instr_mem (
    input  wire [31:0] addr,      // byte address (PC)
    output wire [31:0] instr
);
    // 256 words = 1KB of instruction memory
    reg [31:0] mem [0:255];

    initial begin
        // Load a hex program here, e.g.:
        // $readmemh("program.hex", mem);
        // For simulation you can also preload manually in the testbench.
    end

    // word-align: ignore lower 2 bits of byte address
    assign instr = mem[addr[9:2]];
endmodule

assignment-5/pc_reg.v
// pc_reg.v — Program Counter register
module pc_reg (
    input  wire        clk,
    input  wire        rst,
    input  wire [31:0] pc_next,
    output reg  [31:0] pc
);
    always @(posedge clk or posedge rst) begin
        if (rst)
            pc <= 32'h0000_0000;
        else
            pc <= pc_next;
    end
endmodule

assignment-5/riscv_single_cycle.v
// riscv_single_cycle.v — TOP LEVEL: wires every block per the datapath diagram
module riscv_single_cycle (
    input wire clk,
    input wire rst
);

    // ---- PC / fetch ----
    wire [31:0] pc, pc_next, pc_plus4, pc_branch;
    wire [31:0] instr;

    pc_reg u_pc (.clk(clk), .rst(rst), .pc_next(pc_next), .pc(pc));

    adder u_pc_plus4 (.a(pc), .b(32'd4), .sum(pc_plus4));

    instr_mem u_imem (.addr(pc), .instr(instr));

    // ---- Decode fields ----
    wire [6:0] opcode  = instr[6:0];
    wire [4:0] rd_addr = instr[11:7];
    wire [2:0] funct3  = instr[14:12];
    wire [4:0] rs1     = instr[19:15];
    wire [4:0] rs2     = instr[24:20];
    wire       funct7_5 = instr[30];

    // ---- Control signals ----
    wire reg_write, alu_src, mem_write, result_src, branch;
    wire [1:0] imm_src, alu_op;

    control_unit u_ctrl (
        .opcode(opcode), .reg_write(reg_write), .alu_src(alu_src),
        .mem_write(mem_write), .result_src(result_src), .branch(branch),
        .imm_src(imm_src), .alu_op(alu_op)
    );

    wire [3:0] alu_control_sig;
    alu_control u_alu_ctrl (
        .alu_op(alu_op), .funct3(funct3), .funct7_5(funct7_5),
        .alu_control(alu_control_sig)
    );

    // ---- Register file ----
    wire [31:0] reg_rd1, reg_rd2, write_back_data;

    reg_file u_rf (
        .clk(clk), .we3(reg_write),
        .a1(rs1), .a2(rs2), .a3(rd_addr),
        .wd3(write_back_data),
        .rd1(reg_rd1), .rd2(reg_rd2)
    );

    // ---- Immediate generator ----
    wire [31:0] imm_ext;
    imm_gen u_immgen (.instr(instr), .imm_src(imm_src), .imm_ext(imm_ext));

    // ---- ALU operand B mux (ALUSrc) ----
    wire [31:0] alu_b;
    mux2 #(32) u_alu_src_mux (.sel(alu_src), .d0(reg_rd2), .d1(imm_ext), .y(alu_b));

    // ---- ALU ----
    wire [31:0] alu_result;
    wire        alu_zero;
    alu u_alu (
        .a(reg_rd1), .b(alu_b), .alu_control(alu_control_sig),
        .result(alu_result), .zero(alu_zero)
    );

    // ---- Data memory ----
    wire [31:0] mem_read_data;
    data_mem u_dmem (
        .clk(clk), .mem_write(mem_write),
        .addr(alu_result), .write_data(reg_rd2),
        .read_data(mem_read_data)
    );

    // ---- Write-back mux (ResultSrc / MemtoReg) ----
    mux2 #(32) u_wb_mux (
        .sel(result_src), .d0(alu_result), .d1(mem_read_data),
        .y(write_back_data)
    );

    // ---- Branch target & PC mux (PCSrc) ----
    adder u_pc_branch (.a(pc), .b(imm_ext), .sum(pc_branch));

    wire pc_src = branch & alu_zero;
    mux2 #(32) u_pc_mux (.sel(pc_src), .d0(pc_plus4), .d1(pc_branch), .y(pc_next));

endmodule

assignment-5/riscv_tb.v
// riscv_tb.v — Simple testbench for the single-cycle RV32I core
`timescale 1ns/1ps
module riscv_tb;
    reg clk = 0;
    reg rst = 1;

    riscv_single_cycle dut (.clk(clk), .rst(rst));

    // 100MHz-equivalent clock for simulation
    always #5 clk = ~clk;

    initial begin
        // Dump signals for GTKWave
        $dumpfile("wave.vcd");
        $dumpvars(0, riscv_tb);

        // Preload a tiny test program directly into instruction memory.
        // Example program (machine code, RV32I):
        //   addi x1, x0, 5      -> 0x00500093
        //   addi x2, x0, 10     -> 0x00A00113
        //   add  x3, x1, x2     -> 0x002081B3
        //   sw   x3, 0(x0)      -> 0x00302023
        //   lw   x4, 0(x0)      -> 0x00002203
        dut.u_imem.mem[0] = 32'h00500093;
        dut.u_imem.mem[1] = 32'h00A00113;
        dut.u_imem.mem[2] = 32'h002081B3;
        dut.u_imem.mem[3] = 32'h00302023;
        dut.u_imem.mem[4] = 32'h00002203;

        #10 rst = 0;

        #100;
        $display("x1 = %0d", dut.u_rf.regs[1]);
        $display("x2 = %0d", dut.u_rf.regs[2]);
        $display("x3 = %0d", dut.u_rf.regs[3]);
        $display("x4 = %0d", dut.u_rf.regs[4]);
        $display("mem[0] = %0d", dut.u_dmem.mem[0]);

        $finish;
    end
endmodule

assignment-5/wave.vcd
$date
	Wed Aug 19 22:04:36 2026
$end
$version
	Icarus Verilog
$end
$timescale
	1ps
$end
$scope module riscv_tb $end
$var reg 1 ! clk $end
$var reg 1 " rst $end
$scope module dut $end
$var wire 1 ! clk $end
$var wire 1 # pc_src $end
$var wire 1 " rst $end
$var wire 32 $ write_back_data [31:0] $end
$var wire 5 % rs2 [4:0] $end
$var wire 5 & rs1 [4:0] $end
$var wire 1 ' result_src $end
$var wire 1 ( reg_write $end
$var wire 32 ) reg_rd2 [31:0] $end
$var wire 32 * reg_rd1 [31:0] $end
$var wire 5 + rd_addr [4:0] $end
$var wire 32 , pc_plus4 [31:0] $end
$var wire 32 - pc_next [31:0] $end
$var wire 32 . pc_branch [31:0] $end
$var wire 32 / pc [31:0] $end
$var wire 7 0 opcode [6:0] $end
$var wire 1 1 mem_write $end
$var wire 32 2 mem_read_data [31:0] $end
$var wire 32 3 instr [31:0] $end
$var wire 2 4 imm_src [1:0] $end
$var wire 32 5 imm_ext [31:0] $end
$var wire 1 6 funct7_5 $end
$var wire 3 7 funct3 [2:0] $end
$var wire 1 8 branch $end
$var wire 1 9 alu_zero $end
$var wire 1 : alu_src $end
$var wire 32 ; alu_result [31:0] $end
$var wire 2 < alu_op [1:0] $end
$var wire 4 = alu_control_sig [3:0] $end
$var wire 32 > alu_b [31:0] $end
$scope module u_alu $end
$var wire 1 9 zero $end
$var wire 32 ? b [31:0] $end
$var wire 4 @ alu_control [3:0] $end
$var wire 32 A a [31:0] $end
$var reg 32 B result [31:0] $end
$upscope $end
$scope module u_alu_ctrl $end
$var wire 3 C funct3 [2:0] $end
$var wire 1 6 funct7_5 $end
$var wire 2 D alu_op [1:0] $end
$var reg 4 E alu_control [3:0] $end
$upscope $end
$scope module u_alu_src_mux $end
$var wire 32 F y [31:0] $end
$var wire 1 : sel $end
$var wire 32 G d1 [31:0] $end
$var wire 32 H d0 [31:0] $end
$var parameter 32 I WIDTH $end
$upscope $end
$scope module u_ctrl $end
$var wire 7 J opcode [6:0] $end
$var parameter 7 K BRANCH $end
$var parameter 7 L I_TYPE_A $end
$var parameter 7 M LOAD $end
$var parameter 7 N R_TYPE $end
$var parameter 7 O STORE $end
$var reg 2 P alu_op [1:0] $end
$var reg 1 : alu_src $end
$var reg 1 8 branch $end
$var reg 2 Q imm_src [1:0] $end
$var reg 1 1 mem_write $end
$var reg 1 ( reg_write $end
$var reg 1 ' result_src $end
$upscope $end
$scope module u_dmem $end
$var wire 32 R addr [31:0] $end
$var wire 1 ! clk $end
$var wire 1 1 mem_write $end
$var wire 32 S read_data [31:0] $end
$var wire 32 T write_data [31:0] $end
$var integer 32 U i [31:0] $end
$upscope $end
$scope module u_imem $end
$var wire 32 V instr [31:0] $end
$var wire 32 W addr [31:0] $end
$upscope $end
$scope module u_immgen $end
$var wire 2 X imm_src [1:0] $end
$var wire 32 Y instr [31:0] $end
$var reg 32 Z imm_ext [31:0] $end
$upscope $end
$scope module u_pc $end
$var wire 1 ! clk $end
$var wire 1 " rst $end
$var wire 32 [ pc_next [31:0] $end
$var reg 32 \ pc [31:0] $end
$upscope $end
$scope module u_pc_branch $end
$var wire 32 ] a [31:0] $end
$var wire 32 ^ b [31:0] $end
$var wire 32 _ sum [31:0] $end
$upscope $end
$scope module u_pc_mux $end
$var wire 32 ` d1 [31:0] $end
$var wire 1 # sel $end
$var wire 32 a y [31:0] $end
$var wire 32 b d0 [31:0] $end
$var parameter 32 c WIDTH $end
$upscope $end
$scope module u_pc_plus4 $end
$var wire 32 d a [31:0] $end
$var wire 32 e b [31:0] $end
$var wire 32 f sum [31:0] $end
$upscope $end
$scope module u_rf $end
$var wire 5 g a1 [4:0] $end
$var wire 5 h a2 [4:0] $end
$var wire 5 i a3 [4:0] $end
$var wire 1 ! clk $end
$var wire 1 ( we3 $end
$var wire 32 j wd3 [31:0] $end
$var wire 32 k rd2 [31:0] $end
$var wire 32 l rd1 [31:0] $end
$var integer 32 m i [31:0] $end
$upscope $end
$scope module u_wb_mux $end
$var wire 32 n d0 [31:0] $end
$var wire 32 o d1 [31:0] $end
$var wire 1 ' sel $end
$var wire 32 p y [31:0] $end
$var parameter 32 q WIDTH $end
$upscope $end
$upscope $end
$upscope $end
$enddefinitions $end
$comment Show the parameter values. $end
$dumpall
b100000 q
b100000 c
b100011 O
b110011 N
b11 M
b10011 L
b1100011 K
b100000 I
$end
#0
$dumpvars
b101 p
b0 o
b101 n
b100000 m
b0 l
b0 k
b101 j
b1 i
b101 h
b0 g
b100 f
b100 e
b0 d
b100 b
b100 a
b101 `
b101 _
b101 ^
b0 ]
b0 \
b100 [
b101 Z
b10100000000000010010011 Y
b0 X
b0 W
b10100000000000010010011 V
b100000000 U
b0 T
b0 S
b101 R
b0 Q
b10 P
b10011 J
b0 H
b101 G
b101 F
b0 E
b10 D
b0 C
b101 B
b0 A
b0 @
b101 ?
b101 >
b0 =
b10 <
b101 ;
1:
09
08
b0 7
06
b101 5
b0 4
b10100000000000010010011 3
b0 2
01
b10011 0
b0 /
b101 .
b100 -
b100 ,
b1 +
b0 *
b0 )
1(
0'
b0 &
b101 %
b101 $
0#
1"
0!
$end
#5000
1!
#10000
0!
0"
#15000
b1010 $
b1010 j
b1010 p
b1010 ;
b1010 B
b1010 R
b1010 n
b1010 >
b1010 ?
b1010 F
b1010 5
b1010 G
b1010 Z
b1010 ^
b1010 %
b1010 h
b10 +
b10 i
b1000 -
b1000 [
b1000 a
b101000000000000100010011 3
b101000000000000100010011 V
b101000000000000100010011 Y
b1110 .
b1110 _
b1110 `
b1000 ,
b1000 b
b1000 f
b100 /
b100 W
b100 \
b100 ]
b100 d
1!
#20000
0!
#25000
b1111 $
b1111 j
b1111 p
b1111 ;
b1111 B
b1111 R
b1111 n
b1010 )
b1010 H
b1010 T
b1010 k
b101 *
b101 A
b101 l
b10 <
b10 D
b10 P
0:
1(
b10 5
b10 G
b10 Z
b10 ^
b10 %
b10 h
b1 &
b1 g
b11 +
b11 i
b110011 0
b110011 J
b1100 -
b1100 [
b1100 a
b1000001000000110110011 3
b1000001000000110110011 V
b1000001000000110110011 Y
b1010 .
b1010 _
b1010 `
b1100 ,
b1100 b
b1100 f
b1000 /
b1000 W
b1000 \
b1000 ]
b1000 d
1!
#30000
0!
#35000
19
b0 $
b0 j
b0 p
b0 ;
b0 B
b0 R
b0 n
b0 >
b0 ?
b0 F
b1111 )
b1111 H
b1111 T
b1111 k
b0 *
b0 A
b0 l
b1 4
b1 Q
b1 X
11
1:
b0 <
b0 D
b0 P
0(
b0 5
b0 G
b0 Z
b0 ^
b11 %
b11 h
b0 &
b0 g
b10 7
b10 C
b0 +
b0 i
b100011 0
b100011 J
b10000 -
b10000 [
b10000 a
b1100000010000000100011 3
b1100000010000000100011 V
b1100000010000000100011 Y
b1100 .
b1100 _
b1100 `
b10000 ,
b10000 b
b10000 f
b1100 /
b1100 W
b1100 \
b1100 ]
b1100 d
1!
#40000
0!
#45000
19
b0 ;
b0 B
b0 R
b0 n
b1111 $
b1111 j
b1111 p
b0 >
b0 ?
b0 F
b0 )
b0 H
b0 T
b0 k
1'
1(
b0 4
b0 Q
b0 X
01
1:
b0 5
b0 G
b0 Z
b0 ^
b0 %
b0 h
b100 +
b100 i
b11 0
b11 J
b10100 -
b10100 [
b10100 a
b10001000000011 3
b10001000000011 V
b10001000000011 Y
b1111 2
b1111 S
b1111 o
b10000 .
b10000 _
b10000 `
b10100 ,
b10100 b
b10100 f
b10000 /
b10000 W
b10000 \
b10000 ]
b10000 d
1!
#50000
0!
#55000
bx 2
bx S
bx o
x9
bx ;
bx B
bx R
bx n
bx $
bx j
bx p
bx >
bx ?
bx F
bx )
bx H
bx T
bx k
bx *
bx A
bx l
0'
0:
0(
bx 5
bx G
bx Z
bx ^
x6
bx %
bx h
bx &
bx g
bx 7
bx C
bx +
bx i
bx 0
bx J
b11000 -
b11000 [
b11000 a
bx 3
bx V
bx Y
bx .
bx _
bx `
b11000 ,
b11000 b
b11000 f
b10100 /
b10100 W
b10100 \
b10100 ]
b10100 d
1!
#60000
0!
#65000
b11100 -
b11100 [
b11100 a
b11100 ,
b11100 b
b11100 f
b11000 /
b11000 W
b11000 \
b11000 ]
b11000 d
1!
#70000
0!
#75000
b100000 -
b100000 [
b100000 a
b100000 ,
b100000 b
b100000 f
b11100 /
b11100 W
b11100 \
b11100 ]
b11100 d
1!
#80000
0!
#85000
b100100 -
b100100 [
b100100 a
b100100 ,
b100100 b
b100100 f
b100000 /
b100000 W
b100000 \
b100000 ]
b100000 d
1!
#90000
0!
#95000
b101000 -
b101000 [
b101000 a
b101000 ,
b101000 b
b101000 f
b100100 /
b100100 W
b100100 \
b100100 ]
b100100 d
1!
#100000
0!
#105000
b101100 -
b101100 [
b101100 a
b101100 ,
b101100 b
b101100 f
b101000 /
b101000 W
b101000 \
b101000 ]
b101000 d
1!
