assignment-3/alu8.v
// alu8.v
// 8-bit ALU supporting ADD / AND / OR / XOR / NOT, plus a carry-out
// flag for the ADD case. (Functionally identical to the original
// "eight_bit_alu" module - encoding of `sel` is unchanged.)

module alu8(
    input  [7:0] a,
    input  [7:0] b,
    input  [2:0] sel,
    output reg [7:0] o,
    output reg       c
    );

    always @(*) begin
        c = 1'b0;
        case (sel)
            3'b001 : {c, o} = a + b;   // ADD
            3'b010 : o = a & b;       // AND
            3'b011 : o = a | b;       // OR
            3'b100 : o = a ^ b;       // XOR
            3'b101 : o = ~a;          // NOT
            default: {c, o} = 9'b0;
        endcase
    end

endmodule

assignment-3/opamux.v
// opamux.v
// Selects whether ALU operand-1 comes from the immediate byte or
// from the (possibly negated) register value.
// (Functionally identical to the original "immux" module.)

module opa_mux(
    input  [7:0] imm_in,
    input  [7:0] reg_in,
    input        sel,
    output reg [7:0] opa_out
    );

    always @(*) begin
        if (sel)
            opa_out = imm_in;
        else
            opa_out = reg_in;
    end

endmodule

assignment-3/subsel.v
// subsel.v
// Chooses between the negated operand (for subtraction) and the
// plain operand (for addition/pass-through).
// (Functionally identical to the original "compmux" module.)

module sub_mux(
    input  [7:0] neg_in,
    input  [7:0] plain_in,
    input        sel,
    output reg [7:0] out_val
    );

    always @(*) begin
        if (sel)
            out_val = neg_in;
        else
            out_val = plain_in;
    end

endmodule

assignment-3/negate.v
// negate.v
// Produces the two's-complement negation of an 8-bit input.
// (Functionally identical to the original "compi" module.)

module twos_comp(
    input  [7:0] in_val,
    output reg [7:0] neg_val
    );

    always @(*) begin
        neg_val = ~in_val + 1'b1;
    end

endmodule

assignment-3/regfile.v
// regfile.v
// 8 x 8-bit register file with two read ports and one write port.
// Register 6 is hard-wired to the constant 1 and register 7 is
// hard-wired to the constant 0; writes to either are ignored.
// (Functionally identical to the original "refile" module.)

module regfile_unit(
    input        clk,
    input  [2:0] rd_addr1,
    input  [2:0] rd_addr2,
    input  [2:0] wr_addr,
    input  [7:0] wr_data,
    input        wr_en,
    output reg [7:0] rd_data1,
    output reg [7:0] rd_data2
    );

    reg [7:0] regmem [0:7];
    integer k;

    initial begin
        for (k = 0; k < 8; k = k + 1)
            regmem[k] = 8'b0;
    end

    always @(posedge clk) begin
        if (wr_en) begin
            case (wr_addr)
                3'd6: regmem[6] <= 8'd1;   // constant register, ignores writes
                3'd7: regmem[7] <= 8'd0;   // constant register, ignores writes
                default: regmem[wr_addr] <= wr_data;
            endcase
        end
    end

    always @(*) begin
        case (rd_addr1)
            3'd6: rd_data1 = 8'd1;
            3'd7: rd_data1 = 8'd0;
            default: rd_data1 = regmem[rd_addr1];
        endcase

        case (rd_addr2)
            3'd6: rd_data2 = 8'd1;
            3'd7: rd_data2 = 8'd0;
            default: rd_data2 = regmem[rd_addr2];
        endcase
    end

endmodule

assignment-3/ctrl_unit.v
// ctrl_unit.v
// Instruction decoder / finite-state-machine controller.
// Drives the register file, ALU operand muxes and the ALU op-select
// signal from the current 8-bit instruction byte.
// (Functionally identical to the original "control" module - the
// instruction encoding and timing are unchanged.)

module ctrl_unit(
    input        clk,
    input  [7:0] instr,
    output reg [7:0] imm_out,
    output reg [2:0] rd_sel1,     // -> straight to ALU operand2
    output reg [2:0] rd_sel2,     // -> through 2's-comp/imm mux -> ALU operand1
    output reg [2:0] wr_sel,
    output reg       wr_en,
    output reg [2:0] alu_sel,
    output reg       neg_sel,     // 2's-complement mux control (subtract)
    output reg       imm_sel,     // immediate mux control
    output reg       pc_en
    );

    localparam [2:0] ACC_ADDR = 3'b000;   // accumulator register address
    localparam [2:0] G_ADDR   = 3'b110;   // hard-wired constant = 8'd1
    localparam [2:0] H_ADDR   = 3'b111;   // hard-wired constant = 8'd0

    // ALU sel encoding as implemented in alu8.v (must match alu8.v)
    localparam [2:0] ALU_ADD  = 3'b001;
    localparam [2:0] ALU_AND  = 3'b010;
    localparam [2:0] ALU_OR   = 3'b011;
    localparam [2:0] ALU_XOR  = 3'b100;
    localparam [2:0] ALU_NOT  = 3'b101;

    localparam [1:0] ST_DECODE = 2'b00;
    localparam [1:0] ST_FETCH  = 2'b01;
    localparam [1:0] ST_EXEC   = 2'b10;

    reg [1:0] state;

    always @(*) begin
        wr_en = (state == ST_EXEC);
        pc_en = (state != ST_EXEC);   // hold PC during writeback cycle
    end

    initial begin
        state   = ST_DECODE;
        imm_out = 8'd0;
        rd_sel1 = 3'd0;
        rd_sel2 = 3'd0;
        wr_sel  = 3'd0;
        alu_sel = 3'd0;
        neg_sel = 1'b0;
        imm_sel = 1'b0;
    end

    always @(posedge clk) begin
        case (state)

            ST_DECODE: begin
                neg_sel <= 1'b0;

                case (instr[7:6])

                    2'b00: begin // mov reg <- reg
                        rd_sel2 <= instr[2:0];   // source -> operand2 path (imm_sel=0, neg_sel=0)
                        rd_sel1 <= H_ADDR;       // constant 0
                        wr_sel  <= instr[5:3];   // destination
                        alu_sel <= ALU_ADD;      // a+0 = pass-through
                        imm_sel <= 1'b0;
                        state   <= ST_EXEC;
                    end

                    2'b01: begin // mov reg <- immediate
                        wr_sel  <= instr[5:3];
                        rd_sel1 <= H_ADDR;       // constant 0
                        rd_sel2 <= H_ADDR;       // don't-care, overridden by imm_sel
                        alu_sel <= ALU_ADD;      // imm+0 = pass-through
                        imm_sel <= 1'b1;
                        state   <= ST_FETCH;     // next byte is data, not an opcode
                    end

                    2'b10: begin
                        wr_sel  <= ACC_ADDR;     // ALU result always -> accumulator
                        imm_sel <= 1'b0;

                        case (instr[2:0])
                            3'b001: begin // ADD : ACC + R
                                rd_sel2 <= ACC_ADDR;
                                rd_sel1 <= instr[5:3];
                                alu_sel <= ALU_ADD;
                                neg_sel <= 1'b0;
                            end
                            3'b010: begin // INC : ACC + 1
                                rd_sel2 <= ACC_ADDR;
                                rd_sel1 <= G_ADDR;
                                alu_sel <= ALU_ADD;
                                neg_sel <= 1'b0;
                            end
                            3'b011: begin // DEC : ACC - 1, via 2's complement
                                rd_sel1 <= ACC_ADDR;
                                rd_sel2 <= G_ADDR;   // negated by neg_sel -> -1
                                alu_sel <= ALU_ADD;
                                neg_sel <= 1'b1;
                            end
                            3'b100: begin // XOR : ACC ^ R
                                rd_sel2 <= ACC_ADDR;
                                rd_sel1 <= instr[5:3];
                                alu_sel <= ALU_XOR;
                                neg_sel <= 1'b0;
                            end
                            3'b101: begin // AND : ACC & R
                                rd_sel2 <= ACC_ADDR;
                                rd_sel1 <= instr[5:3];
                                alu_sel <= ALU_AND;
                                neg_sel <= 1'b0;
                            end
                            3'b110: begin // OR : ACC | R
                                rd_sel2 <= ACC_ADDR;
                                rd_sel1 <= instr[5:3];
                                alu_sel <= ALU_OR;
                                neg_sel <= 1'b0;
                            end
                            3'b111: begin // NOT : ~ACC (unary)
                                rd_sel2 <= ACC_ADDR;
                                rd_sel1 <= H_ADDR;
                                alu_sel <= ALU_NOT;
                                neg_sel <= 1'b0;
                            end
                            default: begin
                                rd_sel2 <= ACC_ADDR;
                                rd_sel1 <= instr[5:3];
                                alu_sel <= ALU_ADD;
                                neg_sel <= 1'b0;
                            end
                        endcase

                        state <= ST_EXEC;
                    end

                    default: state <= ST_DECODE;

                endcase
            end

            ST_FETCH: begin
                imm_out <= instr;
                state   <= ST_EXEC;
            end

            ST_EXEC: begin
                state <= ST_DECODE;
            end

            default: state <= ST_DECODE;
        endcase
    end

endmodule

assignment-3/progmem.v
// progmem.v
// Instruction memory pre-loaded with a small demo program that
// exercises MOV(reg<-reg), MOV(reg<-imm), ADD, INC, DEC, XOR, AND,
// OR and NOT. (Functionally identical to the original "imem" module.)

module progmem(
    input  [7:0] addr,
    output reg [7:0] data
    );

    reg [7:0] rom [0:255];
    integer idx;

    initial begin
        rom[8'h00] = 8'h40; // mov ACC(r0) <- imm
        rom[8'h01] = 8'h0A; //   imm = 10            -> ACC = 10
        rom[8'h02] = 8'h48; // mov r1 <- imm
        rom[8'h03] = 8'h05; //   imm = 5             -> r1 = 5
        rom[8'h04] = 8'h11; // mov r2 <- r1 (reg<-reg demo) -> r2 = 5
        rom[8'h05] = 8'h89; // ADD  ACC + r1  = 10 + 5      -> ACC = 15
        rom[8'h06] = 8'h92; // INC  ACC + 1   = 15 + 1      -> ACC = 16
        rom[8'h07] = 8'h9B; // DEC  ACC - 1   = 16 - 1      -> ACC = 15
        rom[8'h08] = 8'h58; // mov r3 <- imm
        rom[8'h09] = 8'hF0; //   imm = 0xF0 (240)   -> r3 = 240
        rom[8'h0A] = 8'h9C; // XOR  ACC ^ r3  = 15 ^ 240    -> ACC = 255
        rom[8'h0B] = 8'h60; // mov r4 <- imm
        rom[8'h0C] = 8'h0F; //   imm = 0x0F (15)    -> r4 = 15
        rom[8'h0D] = 8'hA5; // AND  ACC & r4 = 255 & 15    -> ACC = 15
        rom[8'h0E] = 8'h68; // mov r5 <- imm
        rom[8'h0F] = 8'hAA; //   imm = 0xAA (170)   -> r5 = 170
        rom[8'h10] = 8'hAE; // OR   ACC | r5  = 15 | 170    -> ACC = 175
        rom[8'h11] = 8'hBF; // NOT  ~ACC      = ~175        -> ACC = 80
        for (idx = 18; idx < 256; idx = idx + 1)
            rom[idx] = 8'h00; // NOP (mov r0<-r0) padding
    end

    always @(*) begin
        data = rom[addr];
    end

endmodule

assignment-3/pcinc.v
// pcinc.v
// Combinational "PC + 1" adder used to compute the next program-counter
// value. (Functionally identical to the original "pc_adder" module.)

module pc_inc(
    input  [7:0] pc_cur,
    output [7:0] pc_next
    );

    assign pc_next = pc_cur + 8'd1;

endmodule

assignment-3/processor.v
`timescale 1ns/1ps

// processor.v
// Top-level tie-together of program counter, program memory, control
// unit, register file and ALU datapath.
// (Functionally identical to the original "cpu" module.)

module processor(
    input clk
    );

    reg  [7:0] pc;
    wire [7:0] pc_next;
    wire       pc_en_w;

    pc_inc u_pc_inc (
        .pc_cur  (pc),
        .pc_next (pc_next)
    );

    initial pc = 8'd0;
    always @(posedge clk) if (pc_en_w) pc <= pc_next;

    wire [7:0] instr;

    progmem u_progmem (
        .addr (pc),
        .data (instr)
    );

    wire [7:0] imm_w;
    wire [2:0] rsel1_w;     // -> straight to ALU operand2
    wire [2:0] rsel2_w;     // -> 2's-comp / imm mux -> ALU operand1
    wire [2:0] wsel_w;
    wire       wen_w;
    wire [2:0] aluop_w;
    wire       negsel_w;
    wire       immsel_w;

    ctrl_unit u_ctrl_unit (
        .clk     (clk),
        .instr   (instr),
        .imm_out (imm_w),
        .rd_sel1 (rsel1_w),
        .rd_sel2 (rsel2_w),
        .wr_sel  (wsel_w),
        .wr_en   (wen_w),
        .alu_sel (aluop_w),
        .neg_sel (negsel_w),
        .imm_sel (immsel_w),
        .pc_en   (pc_en_w)
    );

    wire [7:0] rdata1_w;    // direct  -> ALU operand2
    wire [7:0] rdata2_w;    // muxed   -> ALU operand1
    wire [7:0] alu_res_w;

    regfile_unit u_regfile (
        .clk      (clk),
        .rd_addr1 (rsel1_w),
        .rd_addr2 (rsel2_w),
        .wr_addr  (wsel_w),
        .wr_data  (alu_res_w),
        .wr_en    (wen_w),
        .rd_data1 (rdata1_w),
        .rd_data2 (rdata2_w)
    );

    wire [7:0] neg_out_w;
    wire [7:0] opA_pre_w;   // result of neg_sel mux: rdata2_w or -rdata2_w

    twos_comp u_twos_comp (
        .in_val  (rdata2_w),
        .neg_val (neg_out_w)
    );

    sub_mux u_sub_mux (
        .neg_in   (neg_out_w),
        .plain_in (rdata2_w),
        .sel      (negsel_w),
        .out_val  (opA_pre_w)
    );

    //--------------------------------------------------------------
    // Immediate MUX  (imm_w vs opA_pre_w) -> ALU operand1
    //--------------------------------------------------------------
    wire [7:0] operand1_w;

    opa_mux u_opa_mux (
        .imm_in  (imm_w),
        .reg_in  (opA_pre_w),
        .sel     (immsel_w),
        .opa_out (operand1_w)
    );

    //--------------------------------------------------------------
    // ALU
    //--------------------------------------------------------------
    wire alu_carry_w;

    alu8 u_alu8 (
        .a   (operand1_w),   // operand1
        .b   (rdata1_w),     // operand2 (direct)
        .sel (aluop_w),
        .o   (alu_res_w),
        .c   (alu_carry_w)
    );

endmodule

assignment-3/processor_tb.v
`timescale 1ns/1ps

// processor_tb.v
// Simple clock-driven testbench: runs the processor for 40 clock
// edges, prints PC / instruction / register contents each cycle, and
// dumps a VCD waveform for GTKWave.
// (Functionally identical to the original "tb_cpu" module.)

module processor_tb;

    reg clk = 0;
    always #5 clk = ~clk;

    processor dut (.clk(clk));

    integer i;

    initial begin
        $dumpfile("processor.vcd");
        $dumpvars(0, processor_tb);

        $display("time  pc   inst   ACC(r0) r1  r2  r3  r4  r5");
        for (i = 0; i < 40; i = i + 1) begin
            @(posedge clk);
            #1;
            $display("%0t  %0d   %0h    %0d  %0d  %0d  %0d  %0d  %0d",
                $time, dut.pc, dut.instr,
                dut.u_regfile.regmem[0],
                dut.u_regfile.regmem[1],
                dut.u_regfile.regmem[2],
                dut.u_regfile.regmem[3],
                dut.u_regfile.regmem[4],
                dut.u_regfile.regmem[5]);
        end
        $finish;
    end

endmodule

assignment-3/processor.vcd
$date
	Thu Jul 16 07:55:45 2026
$end
$version
	Icarus Verilog
$end
$timescale
	1ps
$end
$scope module processor_tb $end
$var reg 1 ! clk $end
$var integer 32 " i [31:0] $end
$scope module dut $end
$var wire 1 ! clk $end
$var wire 3 # wsel_w [2:0] $end
$var wire 1 $ wen_w $end
$var wire 3 % rsel2_w [2:0] $end
$var wire 3 & rsel1_w [2:0] $end
$var wire 8 ' rdata2_w [7:0] $end
$var wire 8 ( rdata1_w [7:0] $end
$var wire 8 ) pc_next [7:0] $end
$var wire 1 * pc_en_w $end
$var wire 8 + operand1_w [7:0] $end
$var wire 8 , opA_pre_w [7:0] $end
$var wire 1 - negsel_w $end
$var wire 8 . neg_out_w [7:0] $end
$var wire 8 / instr [7:0] $end
$var wire 1 0 immsel_w $end
$var wire 8 1 imm_w [7:0] $end
$var wire 3 2 aluop_w [2:0] $end
$var wire 8 3 alu_res_w [7:0] $end
$var wire 1 4 alu_carry_w $end
$var reg 8 5 pc [7:0] $end
$scope module u_alu8 $end
$var wire 3 6 sel [2:0] $end
$var wire 8 7 b [7:0] $end
$var wire 8 8 a [7:0] $end
$var reg 1 4 c $end
$var reg 8 9 o [7:0] $end
$upscope $end
$scope module u_ctrl_unit $end
$var wire 1 ! clk $end
$var wire 8 : instr [7:0] $end
$var parameter 3 ; ACC_ADDR $end
$var parameter 3 < ALU_ADD $end
$var parameter 3 = ALU_AND $end
$var parameter 3 > ALU_NOT $end
$var parameter 3 ? ALU_OR $end
$var parameter 3 @ ALU_XOR $end
$var parameter 3 A G_ADDR $end
$var parameter 3 B H_ADDR $end
$var parameter 2 C ST_DECODE $end
$var parameter 2 D ST_EXEC $end
$var parameter 2 E ST_FETCH $end
$var reg 3 F alu_sel [2:0] $end
$var reg 8 G imm_out [7:0] $end
$var reg 1 0 imm_sel $end
$var reg 1 - neg_sel $end
$var reg 1 * pc_en $end
$var reg 3 H rd_sel1 [2:0] $end
$var reg 3 I rd_sel2 [2:0] $end
$var reg 2 J state [1:0] $end
$var reg 1 $ wr_en $end
$var reg 3 K wr_sel [2:0] $end
$upscope $end
$scope module u_opa_mux $end
$var wire 8 L imm_in [7:0] $end
$var wire 1 0 sel $end
$var wire 8 M reg_in [7:0] $end
$var reg 8 N opa_out [7:0] $end
$upscope $end
$scope module u_pc_inc $end
$var wire 8 O pc_cur [7:0] $end
$var wire 8 P pc_next [7:0] $end
$upscope $end
$scope module u_progmem $end
$var wire 8 Q addr [7:0] $end
$var reg 8 R data [7:0] $end
$var integer 32 S idx [31:0] $end
$upscope $end
$scope module u_regfile $end
$var wire 1 ! clk $end
$var wire 3 T rd_addr1 [2:0] $end
$var wire 3 U rd_addr2 [2:0] $end
$var wire 3 V wr_addr [2:0] $end
$var wire 8 W wr_data [7:0] $end
$var wire 1 $ wr_en $end
$var reg 8 X rd_data1 [7:0] $end
$var reg 8 Y rd_data2 [7:0] $end
$var integer 32 Z k [31:0] $end
$upscope $end
$scope module u_sub_mux $end
$var wire 8 [ plain_in [7:0] $end
$var wire 1 - sel $end
$var wire 8 \ neg_in [7:0] $end
$var reg 8 ] out_val [7:0] $end
$upscope $end
$scope module u_twos_comp $end
$var wire 8 ^ in_val [7:0] $end
$var reg 8 _ neg_val [7:0] $end
$upscope $end
$upscope $end
$upscope $end
$enddefinitions $end
$comment Show the parameter values. $end
$dumpall
b1 E
b10 D
b0 C
b111 B
b110 A
b100 @
b11 ?
b101 >
b10 =
b1 <
b0 ;
$end
#0
$dumpvars
b0 _
b0 ^
b0 ]
b0 \
b0 [
b1000 Z
b0 Y
b0 X
b0 W
b0 V
b0 U
b0 T
b100000000 S
b1000000 R
b0 Q
b1 P
b0 O
b0 N
b0 M
b0 L
b0 K
b0 J
b0 I
b0 H
b0 G
b0 F
b1000000 :
b0 9
b0 8
b0 7
b0 6
b0 5
04
b0 3
b0 2
b0 1
00
b1000000 /
b0 .
0-
b0 ,
b0 +
1*
b1 )
b0 (
b0 '
b0 &
b0 %
0$
b0 #
b0 "
0!
$end
#5000
b1010 /
b1010 :
b1010 R
b1 J
10
b1 2
b1 6
b1 F
b111 %
b111 I
b111 U
b111 &
b111 H
b111 T
b10 )
b10 P
b1 5
b1 O
b1 Q
1!
#6000
b1 "
#10000
0!
#15000
b1010 3
b1010 9
b1010 W
b1001000 /
b1001000 :
b1001000 R
0*
1$
b1010 +
b1010 8
b1010 N
b11 )
b11 P
b10 5
b10 O
b10 Q
b10 J
b1010 1
b1010 G
b1010 L
1!
#16000
b10 "
#20000
0!
#25000
1*
0$
b0 J
1!
#26000
b11 "
#30000
0!
#35000
b101 /
b101 :
b101 R
b100 )
b100 P
b11 5
b11 O
b11 Q
b1 J
b1 #
b1 K
b1 V
1!
#36000
b100 "
#40000
0!
#45000
b101 3
b101 9
b101 W
0*
1$
b101 +
b101 8
b101 N
b10001 /
b10001 :
b10001 R
b10 J
b101 1
b101 G
b101 L
b101 )
b101 P
b100 5
b100 O
b100 Q
1!
#46000
b101 "
#50000
0!
#55000
1*
0$
b0 J
1!
#56000
b110 "
#60000
0!
#65000
b101 3
b101 9
b101 W
b101 ,
b101 M
b101 ]
b11111011 .
b11111011 \
b11111011 _
0*
1$
b101 +
b101 8
b101 N
b101 '
b101 Y
b101 [
b101 ^
b10001001 /
b10001001 :
b10001001 R
b10 J
00
b10 #
b10 K
b10 V
b1 %
b1 I
b1 U
b110 )
b110 P
b101 5
b101 O
b101 Q
1!
#66000
b111 "
#70000
0!
#75000
1*
0$
b0 J
1!
#76000
b1000 "
#80000
0!
#85000
b1010 +
b1010 8
b1010 N
b1010 ,
b1010 M
b1010 ]
b11110110 .
b11110110 \
b11110110 _
b1111 3
b1111 9
b1111 W
0*
1$
b1010 '
b1010 Y
b1010 [
b1010 ^
b101 (
b101 7
b101 X
b10010010 /
b10010010 :
b10010010 R
b10 J
b1 &
b1 H
b1 T
b0 %
b0 I
b0 U
b0 #
b0 K
b0 V
b111 )
b111 P
b110 5
b110 O
b110 Q
1!
#86000
b1001 "
#90000
0!
#95000
b10100 3
b10100 9
b10100 W
b1111 +
b1111 8
b1111 N
b1111 ,
b1111 M
b1111 ]
b11110001 .
b11110001 \
b11110001 _
b1111 '
b1111 Y
b1111 [
b1111 ^
1*
0$
b0 J
1!
#96000
b1010 "
#100000
0!
#105000
b10000 3
b10000 9
b10000 W
0*
1$
b1 (
b1 7
b1 X
b10011011 /
b10011011 :
b10011011 R
b10 J
b110 &
b110 H
b110 T
b1000 )
b1000 P
b111 5
b111 O
b111 Q
1!
#106000
b1011 "
#110000
0!
#115000
b10001 3
b10001 9
b10001 W
b10000 +
b10000 8
b10000 N
b10000 ,
b10000 M
b10000 ]
b11110000 .
b11110000 \
b11110000 _
b10000 '
b10000 Y
b10000 [
b10000 ^
1*
0$
b0 J
1!
#116000
b1100 "
#120000
0!
#125000
14
b11111111 +
b11111111 8
b11111111 N
b11111111 .
b11111111 \
b11111111 _
b1111 3
b1111 9
b1111 W
0*
1$
b11111111 ,
b11111111 M
b11111111 ]
b1 '
b1 Y
b1 [
b1 ^
b10000 (
b10000 7
b10000 X
b1011000 /
b1011000 :
b1011000 R
b10 J
1-
b110 %
b110 I
b110 U
b0 &
b0 H
b0 T
b1001 )
b1001 P
b1000 5
b1000 O
b1000 Q
1!
#126000
b1101 "
#130000
0!
#135000
b1110 3
b1110 9
b1110 W
14
b1111 (
b1111 7
b1111 X
1*
0$
b0 J
1!
#136000
b1110 "
#140000
0!
#145000
b0 .
b0 \
b0 _
b101 3
b101 9
b101 W
04
b101 +
b101 8
b101 N
b0 '
b0 Y
b0 [
b0 ^
b0 (
b0 7
b0 X
b0 ,
b0 M
b0 ]
b11110000 /
b11110000 :
b11110000 R
b1 J
10
b111 %
b111 I
b111 U
b111 &
b111 H
b111 T
b11 #
b11 K
b11 V
0-
b1010 )
b1010 P
b1001 5
b1001 O
b1001 Q
1!
#146000
b1111 "
#150000
0!
#155000
b11110000 3
b11110000 9
b11110000 W
b10011100 /
b10011100 :
b10011100 R
0*
1$
b11110000 +
b11110000 8
b11110000 N
b1011 )
b1011 P
b1010 5
b1010 O
b1010 Q
b10 J
b11110000 1
b11110000 G
b11110000 L
1!
#156000
b10000 "
#160000
0!
#165000
1*
0$
b0 J
1!
#166000
b10001 "
#170000
0!
#175000
b11111111 3
b11111111 9
b11111111 W
b1111 ,
b1111 M
b1111 ]
b11110001 .
b11110001 \
b11110001 _
b1100000 /
b1100000 :
b1100000 R
0*
1$
b1111 '
b1111 Y
b1111 [
b1111 ^
b11110000 (
b11110000 7
b11110000 X
b1111 +
b1111 8
b1111 N
b1100 )
b1100 P
b1011 5
b1011 O
b1011 Q
b10 J
b100 2
b100 6
b100 F
b11 &
b11 H
b11 T
b0 %
b0 I
b0 U
00
b0 #
b0 K
b0 V
1!
#176000
b10010 "
#180000
0!
#185000
b1111 3
b1111 9
b1111 W
b11111111 +
b11111111 8
b11111111 N
b11111111 ,
b11111111 M
b11111111 ]
b1 .
b1 \
b1 _
1*
0$
b11111111 '
b11111111 Y
b11111111 [
b11111111 ^
b0 J
1!
#186000
b10011 "
#190000
0!
#195000
b0 ,
b0 M
b0 ]
b0 .
b0 \
b0 _
b1111 /
b1111 :
b1111 R
b11110000 +
b11110000 8
b11110000 N
b11110000 3
b11110000 9
b11110000 W
b0 '
b0 Y
b0 [
b0 ^
b0 (
b0 7
b0 X
b1101 )
b1101 P
b1100 5
b1100 O
b1100 Q
b1 J
10
b1 2
b1 6
b1 F
b111 %
b111 I
b111 U
b111 &
b111 H
b111 T
b100 #
b100 K
b100 V
1!
#196000
b10100 "
#200000
0!
#205000
b1111 3
b1111 9
b1111 W
0*
1$
b1111 +
b1111 8
b1111 N
b10100101 /
b10100101 :
b10100101 R
b10 J
b1111 1
b1111 G
b1111 L
b1110 )
b1110 P
b1101 5
b1101 O
b1101 Q
1!
#206000
b10101 "
#210000
0!
#215000
1*
0$
b0 J
1!
#216000
b10110 "
#220000
0!
#225000
b11111111 ,
b11111111 M
b11111111 ]
b1 .
b1 \
b1 _
0*
1$
b1111 3
b1111 9
b1111 W
b11111111 '
b11111111 Y
b11111111 [
b11111111 ^
b1111 (
b1111 7
b1111 X
b11111111 +
b11111111 8
b11111111 N
b1101000 /
b1101000 :
b1101000 R
b10 J
b10 2
b10 6
b10 F
b100 &
b100 H
b100 T
b0 %
b0 I
b0 U
00
b0 #
b0 K
b0 V
b1111 )
b1111 P
b1110 5
b1110 O
b1110 Q
1!
#226000
b10111 "
#230000
0!
#235000
b1111 +
b1111 8
b1111 N
b1111 ,
b1111 M
b1111 ]
b11110001 .
b11110001 \
b11110001 _
b1111 '
b1111 Y
b1111 [
b1111 ^
1*
0$
b0 J
1!
#236000
b11000 "
#240000
0!
#245000
b0 ,
b0 M
b0 ]
b0 .
b0 \
b0 _
b0 '
b0 Y
b0 [
b0 ^
b0 (
b0 7
b0 X
b10101010 /
b10101010 :
b10101010 R
b1 J
10
b1 2
b1 6
b1 F
b111 %
b111 I
b111 U
b111 &
b111 H
b111 T
b101 #
b101 K
b101 V
b10000 )
b10000 P
b1111 5
b1111 O
b1111 Q
1!
#246000
b11001 "
#250000
0!
#255000
b10101010 3
b10101010 9
b10101010 W
b10101110 /
b10101110 :
b10101110 R
0*
1$
b10101010 +
b10101010 8
b10101010 N
b10001 )
b10001 P
b10000 5
b10000 O
b10000 Q
b10 J
b10101010 1
b10101010 G
b10101010 L
1!
#256000
b11010 "
#260000
0!
#265000
1*
0$
b0 J
1!
#266000
b11011 "
#270000
0!
#275000
b10101111 3
b10101111 9
b10101111 W
b1111 ,
b1111 M
b1111 ]
b11110001 .
b11110001 \
b11110001 _
b10111111 /
b10111111 :
b10111111 R
0*
1$
b1111 '
b1111 Y
b1111 [
b1111 ^
b10101010 (
b10101010 7
b10101010 X
b1111 +
b1111 8
b1111 N
b10010 )
b10010 P
b10001 5
b10001 O
b10001 Q
b10 J
b11 2
b11 6
b11 F
b101 &
b101 H
b101 T
b0 %
b0 I
b0 U
00
b0 #
b0 K
b0 V
1!
#276000
b11100 "
#280000
0!
#285000
b10101111 +
b10101111 8
b10101111 N
b10101111 ,
b10101111 M
b10101111 ]
b1010001 .
b1010001 \
b1010001 _
1*
0$
b10101111 '
b10101111 Y
b10101111 [
b10101111 ^
b0 J
1!
#286000
b11101 "
#290000
0!
#295000
b0 /
b0 :
b0 R
0*
1$
b1010000 3
b1010000 9
b1010000 W
b0 (
b0 7
b0 X
b10011 )
b10011 P
b10010 5
b10010 O
b10010 Q
b10 J
b101 2
b101 6
b101 F
b111 &
b111 H
b111 T
1!
#296000
b11110 "
#300000
0!
#305000
b10101111 3
b10101111 9
b10101111 W
b1010000 +
b1010000 8
b1010000 N
b1010000 ,
b1010000 M
b1010000 ]
b10110000 .
b10110000 \
b10110000 _
1*
0$
b1010000 '
b1010000 Y
b1010000 [
b1010000 ^
b0 J
1!
#306000
b11111 "
#310000
0!
#315000
0*
1$
b1010000 3
b1010000 9
b1010000 W
b10100 )
b10100 P
b10011 5
b10011 O
b10011 Q
b10 J
b1 2
b1 6
b1 F
1!
#316000
b100000 "
#320000
0!
#325000
1*
0$
b0 J
1!
#326000
b100001 "
#330000
0!
#335000
0*
1$
b10101 )
b10101 P
b10100 5
b10100 O
b10100 Q
b10 J
1!
#336000
b100010 "
#340000
0!
#345000
1*
0$
b0 J
1!
#346000
b100011 "
#350000
0!
#355000
0*
1$
b10110 )
b10110 P
b10101 5
b10101 O
b10101 Q
b10 J
1!
#356000
b100100 "
#360000
0!
#365000
1*
0$
b0 J
1!
#366000
b100101 "
#370000
0!
#375000
0*
1$
b10111 )
b10111 P
b10110 5
b10110 O
b10110 Q
b10 J
1!
#376000
b100110 "
#380000
0!
#385000
1*
0$
b0 J
1!
#386000
b100111 "
#390000
0!
#395000
0*
1$
b11000 )
b11000 P
b10111 5
b10111 O
b10111 Q
b10 J
1!
#396000
b101000 "
