assignment-1/ALU.v
module alu8 (
    input  wire [7:0] A,
    input  wire [7:0] B,
    input  wire [3:0] sel,

    output reg  [7:0] Result,
    output reg        Cout,
    output wire       Zero,
    output reg        Overflow
);

    reg [8:0] temp;

    always @(*) begin
        // Default values
        Result   = 8'b0;
        Cout     = 1'b0;
        Overflow = 1'b0;
        temp     = 9'b0;

        case (sel)

            // ADD
            4'b0000: begin
                temp     = {1'b0, A} + {1'b0, B};
                Result   = temp[7:0];
                Cout     = temp[8];
                Overflow = (A[7] == B[7]) &&
                           (Result[7] != A[7]);
            end

            // SUBTRACT
            4'b0001: begin
                temp     = {1'b0, A} - {1'b0, B};
                Result   = temp[7:0];
                Cout     = temp[8];
                Overflow = (A[7] != B[7]) &&
                           (Result[7] != A[7]);
            end

            // LOGICAL OPERATIONS
            4'b0010: Result = A & B;      // AND
            4'b0011: Result = A | B;      // OR
            4'b0100: Result = A ^ B;      // XOR
            4'b0101: Result = ~(A | B);   // NOR
            4'b0110: Result = ~(A & B);   // NAND
            4'b0111: Result = ~(A ^ B);   // XNOR
            4'b1000: Result = ~A;         // NOT

            // SHIFT OPERATIONS
            4'b1001: Result = A << 1;     // Shift left
            4'b1010: Result = A >> 1;     // Shift right

            // ROTATE OPERATIONS
            4'b1011: Result = {A[6:0], A[7]}; // Rotate left
            4'b1100: Result = {A[0], A[7:1]}; // Rotate right

            // MULTIPLY (lower 8 bits only)
            4'b1101: Result = A * B;

            // COMPARISONS
            4'b1110: Result = {7'b0, (A > B)};
            4'b1111: Result = {7'b0, (A == B)};

            default: Result = 8'b0;

        endcase
    end

    assign Zero = (Result == 8'b0);

endmodule

assignment-1/ALU_tb.v
`timescale 1ns/1ps

module alu8_tb;

    reg  [7:0] A, B;
    reg  [3:0] sel;
    wire [7:0] Result;
    wire Cout, Zero, Overflow;

    alu8 uut (
        .A(A),
        .B(B),
        .sel(sel),
        .Result(Result),
        .Cout(Cout),
        .Zero(Zero),
        .Overflow(Overflow)
    );

    // Execute one test
    task test;
        input [63:0] name;
        input [7:0] a, b;
        input [3:0] op;
        begin
            A   = a;
            B   = b;
            sel = op;
            #10;

        $display("%-8s A=%3d(0x%02h) B=%3d(0x%02h) sel=%b -> R=%3d(0x%02h) C=%b Z=%b V=%b",
             name,
             A, A,
             B, B,
             sel,
             Result, Result,
             Cout,
             Zero,
             Overflow);

       end
    endtask

    initial begin
        $dumpfile("alu.vcd");
        $dumpvars(0, alu8_tb);

        $display("\n============= ALU TEST =============");

        // Basic operations
        test("ADD", 45, 15, 4'b0000);
        test("SUB", 45, 15, 4'b0001);
        test("AND", 45, 15, 4'b0010);
        test("OR",  45, 15, 4'b0011);
        test("XOR", 45, 15, 4'b0100);
        test("NOR", 45, 15, 4'b0101);
        test("NAND",45, 15, 4'b0110);
        test("XNOR",45, 15, 4'b0111);
        test("NOT", 45, 15, 4'b1000);
        test("SLL", 45, 15, 4'b1001);
        test("SRL", 45, 15, 4'b1010);
        test("ROL", 45, 15, 4'b1011);
        test("ROR", 45, 15, 4'b1100);
        test("MUL", 45, 15, 4'b1101);
        test("GT",  45, 15, 4'b1110);
        test("EQ",  45, 15, 4'b1111);

        $display("------------------------------------");

        // Edge cases
        test("ADD_C",   8'hFF, 8'h01, 4'b0000);
        test("SUB_B",   8'd10, 8'd20, 4'b0001);
        test("ZERO",    8'd0,  8'd0,  4'b0011);
        test("ADD_OV",  8'd127,8'd1,  4'b0000);
        test("SUB_OV",  8'h80, 8'h01, 4'b0001);
        test("EQ_T",    8'd99, 8'd99, 4'b1111);

        $display("====================================\n");

        $finish;
    end

endmodule

assignment-1/alu.vcd
$date
	Fri Jun 26 20:34:31 2026
$end
$version
	Icarus Verilog
$end
$timescale
	1ps
$end
$scope module alu8_tb $end
$var wire 1 ! Zero $end
$var wire 8 " Result [7:0] $end
$var wire 1 # Overflow $end
$var wire 1 $ Cout $end
$var reg 8 % A [7:0] $end
$var reg 8 & B [7:0] $end
$var reg 4 ' sel [3:0] $end
$scope module uut $end
$var wire 8 ( A [7:0] $end
$var wire 8 ) B [7:0] $end
$var wire 4 * sel [3:0] $end
$var wire 1 ! Zero $end
$var reg 1 $ Cout $end
$var reg 1 # Overflow $end
$var reg 8 + Result [7:0] $end
$var reg 9 , temp [8:0] $end
$upscope $end
$scope task test $end
$var reg 8 - a [7:0] $end
$var reg 8 . b [7:0] $end
$var reg 64 / name [63:0] $end
$var reg 4 0 op [3:0] $end
$upscope $end
$upscope $end
$enddefinitions $end
$comment Show the parameter values. $end
$dumpall
$end
#0
$dumpvars
b0 0
b10000010100010001000100 /
b1111 .
b101101 -
b111100 ,
b111100 +
b0 *
b1111 )
b101101 (
b0 '
b1111 &
b101101 %
0$
0#
b111100 "
0!
$end
#10000
b11110 ,
0!
b11110 "
b11110 +
b1 '
b1 *
b1 0
b10100110101010101000010 /
#20000
b0 ,
0!
b1101 "
b1101 +
b10 '
b10 *
b10 0
b10000010100111001000100 /
#30000
0!
b101111 "
b101111 +
b11 '
b11 *
b11 0
b100111101010010 /
#40000
0!
b100010 "
b100010 +
b100 '
b100 *
b100 0
b10110000100111101010010 /
#50000
0!
b11010000 "
b11010000 +
b101 '
b101 *
b101 0
b10011100100111101010010 /
#60000
0!
b11110010 "
b11110010 +
b110 '
b110 *
b110 0
b1001110010000010100111001000100 /
#70000
0!
b11011101 "
b11011101 +
b111 '
b111 *
b111 0
b1011000010011100100111101010010 /
#80000
0!
b11010010 "
b11010010 +
b1000 '
b1000 *
b1000 0
b10011100100111101010100 /
#90000
0!
b1011010 "
b1011010 +
b1001 '
b1001 *
b1001 0
b10100110100110001001100 /
#100000
0!
b10110 "
b10110 +
b1010 '
b1010 *
b1010 0
b10100110101001001001100 /
#110000
0!
b1011010 "
b1011010 +
b1011 '
b1011 *
b1011 0
b10100100100111101001100 /
#120000
0!
b10010110 "
b10010110 +
b1100 '
b1100 *
b1100 0
b10100100100111101010010 /
#130000
0!
b10100011 "
b10100011 +
b1101 '
b1101 *
b1101 0
b10011010101010101001100 /
#140000
0!
b1 "
b1 +
b1110 '
b1110 *
b1110 0
b100011101010100 /
#150000
1!
b0 "
b0 +
b1111 '
b1111 *
b1111 0
b100010101010001 /
#160000
1$
b100000000 ,
b0 '
b0 *
b1 &
b1 )
b11111111 %
b11111111 (
b0 0
b1 .
b11111111 -
b100000101000100010001000101111101000011 /
#170000
0!
b11110110 "
b11110110 +
b111110110 ,
1$
b1 '
b1 *
b10100 &
b10100 )
b1010 %
b1010 (
b1 0
b10100 .
b1010 -
b101001101010101010000100101111101000010 /
#180000
b0 ,
0$
1!
b0 "
b0 +
b11 '
b11 *
b0 &
b0 )
b0 %
b0 (
b11 0
b0 .
b0 -
b1011010010001010101001001001111 /
#190000
1#
0!
b10000000 "
b10000000 +
b10000000 ,
b0 '
b0 *
b1 &
b1 )
b1111111 %
b1111111 (
b0 0
b1 .
b1111111 -
b10000010100010001000100010111110100111101010110 /
#200000
b1111111 ,
1#
0!
b1111111 "
b1111111 +
b1 '
b1 *
b10000000 %
b10000000 (
b1 0
b10000000 -
b10100110101010101000010010111110100111101010110 /
#210000
b0 ,
0#
0!
b1 "
b1 +
b1111 '
b1111 *
b1100011 &
b1100011 )
b1100011 %
b1100011 (
b1111 0
b1100011 .
b1100011 -
b1000101010100010101111101010100 /
